{"designerVersion":"1.3.25","favorite":false,"id":"805bf02d-c567-492a-b1b6-0b77daab7260","name":"echangesFragment","type":"fragment","lastUpdate":1512918155157,"rows":[[{"type":"component","dimension":{"xs":12,"sm":12,"md":12,"lg":12},"propertyValues":{"cssClasses":{"type":"constant","value":""},"hidden":{"type":"constant","value":false},"text":{"type":"interpolation","value":"{{setSnippet}}"},"alignment":{"type":"constant","value":"left"}},"reference":"f068e24a-353c-453b-951f-bb8c20447e01","id":"pbText"}],[{"type":"component","dimension":{"xs":12,"sm":12,"md":12,"lg":12},"propertyValues":{"cssClasses":{"type":"constant","value":""},"hidden":{"type":"expression","value":"readOnly"},"readOnly":{"type":"constant","value":false},"required":{"type":"constant","value":false},"minLength":{"type":"constant","value":""},"maxLength":{"type":"constant","value":""},"labelHidden":{"type":"constant","value":false},"label":{"type":"interpolation","value":"Ecrire un commentaire"},"labelPosition":{"type":"constant","value":"top"},"labelWidth":{"type":"constant","value":4},"value":{"type":"variable","value":"comment"}},"reference":"0498eaac-5d5c-4a77-8ca5-f3c3902a5f0b","id":"pbTextarea"}]],"assets":[],"inactiveAssets":[],"data":{"echangesBO":{"type":"constant","exposed":true},"setSnippet":{"type":"expression","value":"//var date = moment(elem.datePostage).locale(\"fr\").format('LLL');\nvar html = '<div class=\"historyWL\">';\n\nif($data.echangesBO && $data.echangesBO.length > 0){\n    $data.echangesBO.forEach(function(elem){\n        \n        html += '<p><span>' + elem.userFullName +\n        '<span class=\"date\">' + moment(elem.datePostage).locale(\"fr\").format('LLL') + \n        '</span></span>' +\n        elem.contenu + '</p>';\n    });\n    html += '</div>';\n}\n\nreturn html;","exposed":false},"comment":{"type":"constant","exposed":true},"readOnly":{"type":"constant","exposed":true}}}